{
  "updated_at": "2026-05-17T18:28:53+00:00",
  "sector_index": {
    "value": 84.3,
    "change_24h": -1.04,
    "change_7d": -15.69,
    "total_mcap_b": 7.38,
    "token_count": 10
  },
  "tokens": {
    "bittensor": {
      "name": "Bittensor",
      "symbol": "TAO",
      "type": "training",
      "company": "Bittensor",
      "price_usd": 269.04,
      "mcap_m": 2577.9,
      "change_24h": -2.33,
      "change_7d": -17.96,
      "volume_m": 146.9,
      "ai_score": null,
      "ai_type": "training",
      "ai_summary": null,
      "verified": true,
      "updated_at": "2026-05-17T18:28:36+00:00"
    },
    "near": {
      "name": "NEAR Protocol",
      "symbol": "NEAR",
      "type": "inference",
      "company": null,
      "price_usd": 1.52,
      "mcap_m": 1965.2,
      "change_24h": 1.28,
      "change_7d": -4.67,
      "volume_m": 148.8,
      "ai_score": null,
      "ai_type": "inference",
      "ai_summary": null,
      "verified": true,
      "updated_at": "2026-05-17T18:28:36+00:00",
      "is_real_ai": false
    },
    "render-token": {
      "name": "Render",
      "symbol": "RENDER",
      "type": "compute",
      "company": null,
      "price_usd": 1.82,
      "mcap_m": 942.3,
      "change_24h": -1.08,
      "change_7d": -11.34,
      "volume_m": 31.0,
      "ai_score": null,
      "ai_type": "compute",
      "ai_summary": null,
      "verified": true,
      "updated_at": "2026-05-17T18:28:36+00:00"
    },
    "venice-token": {
      "name": "Venice Token",
      "symbol": "VVV",
      "type": "inference",
      "company": null,
      "price_usd": 14.18,
      "mcap_m": 653.8,
      "change_24h": 6.54,
      "change_7d": -2.6,
      "volume_m": 60.5,
      "ai_score": null,
      "ai_type": "inference",
      "ai_summary": null,
      "verified": true,
      "updated_at": "2026-05-17T18:28:36+00:00"
    },
    "fetch-ai": {
      "name": "Fetch.ai",
      "symbol": "FET",
      "type": "agents",
      "company": null,
      "price_usd": 0.194499,
      "mcap_m": 439.3,
      "change_24h": -1.44,
      "change_7d": -19.15,
      "volume_m": 31.4,
      "ai_score": null,
      "ai_type": "agents",
      "ai_summary": null,
      "verified": true,
      "updated_at": "2026-05-17T18:28:36+00:00"
    },
    "the-graph": {
      "name": "The Graph",
      "symbol": "GRT",
      "type": "data",
      "company": null,
      "price_usd": 0.025324,
      "mcap_m": 273.5,
      "change_24h": -1.94,
      "change_7d": -11.66,
      "volume_m": 13.3,
      "ai_score": null,
      "ai_type": "data",
      "ai_summary": null,
      "verified": true,
      "updated_at": "2026-05-17T18:28:36+00:00",
      "is_real_ai": false
    },
    "akash-network": {
      "name": "Akash",
      "symbol": "AKT",
      "type": "compute",
      "company": null,
      "price_usd": 0.705061,
      "mcap_m": 205.9,
      "change_24h": 1.16,
      "change_7d": -10.77,
      "volume_m": 5.3,
      "ai_score": null,
      "ai_type": "compute",
      "ai_summary": null,
      "verified": true,
      "updated_at": "2026-05-17T18:28:36+00:00"
    },
    "internet-computer": {
      "name": "Internet Computer",
      "symbol": "ICP",
      "is_real_ai": false,
      "ai_type": "compute",
      "ai_summary": "Blockchain computing platform enabling decentralized applications and AI model hosting at web speed.",
      "ai_score": 70,
      "company": "DFINITY Foundation",
      "price_usd": 2.59,
      "mcap_m": 1431.3,
      "change_24h": -2.52,
      "change_7d": -24.6,
      "volume_m": 41.6,
      "verified": false,
      "updated_at": "2026-05-17T18:28:36+00:00"
    },
    "virtual-protocol": {
      "name": "Virtuals Protocol",
      "symbol": "VIRTUAL",
      "is_real_ai": true,
      "ai_type": "agents",
      "ai_summary": "Protocol for creating and monetizing AI agents with on-chain coordination and co-ownership mechanisms.",
      "ai_score": 80,
      "company": null,
      "price_usd": 0.718994,
      "mcap_m": 472.3,
      "change_24h": -1.09,
      "change_7d": -21.83,
      "volume_m": 35.7,
      "verified": false,
      "updated_at": "2026-05-17T18:28:36+00:00"
    },
    "grass": {
      "name": "Grass",
      "symbol": "GRASS",
      "is_real_ai": true,
      "ai_type": "data",
      "ai_summary": "Decentralized web scraping network that collects training data for AI models through user devices.",
      "ai_score": 75,
      "company": "Wynd Labs",
      "price_usd": 0.300641,
      "mcap_m": 176.5,
      "change_24h": -1.32,
      "change_7d": -21.88,
      "volume_m": 6.2,
      "verified": false,
      "updated_at": "2026-05-17T18:28:36+00:00"
    },
    "origintrail": {
      "name": "OriginTrail",
      "symbol": "TRAC",
      "is_real_ai": true,
      "ai_type": "data",
      "ai_summary": "Decentralized knowledge graph protocol enabling AI agents to access verifiable, structured data across supply chains.",
      "ai_score": 70,
      "company": "Trace Labs",
      "price_usd": 0.327523,
      "mcap_m": 146.5,
      "change_24h": -0.49,
      "change_7d": -7.04,
      "volume_m": 3.2,
      "verified": false,
      "updated_at": "2026-05-17T18:28:36+00:00"
    },
    "arweave": {
      "name": "Arweave",
      "symbol": "AR",
      "is_real_ai": false,
      "ai_type": "data",
      "ai_summary": "Permanent decentralized storage protocol used for storing AI training datasets and model weights permanently.",
      "ai_score": 65,
      "company": null,
      "price_usd": 2.14,
      "mcap_m": 140.9,
      "change_24h": 0.04,
      "change_7d": -15.63,
      "volume_m": 10.2,
      "verified": false,
      "updated_at": "2026-05-17T18:28:36+00:00"
    },
    "eigenlayer": {
      "name": "EigenCloud (prev. EigenLayer)",
      "symbol": "EIGEN",
      "is_real_ai": true,
      "ai_type": "compute",
      "ai_summary": "Ethereum restaking protocol providing infrastructure for decentralized AI compute and verification services.",
      "ai_score": 60,
      "company": "Eigen Labs",
      "price_usd": 0.189173,
      "mcap_m": 140.2,
      "change_24h": -1.11,
      "change_7d": -16.61,
      "volume_m": 11.6,
      "verified": false,
      "updated_at": "2026-05-17T18:28:36+00:00"
    },
    "chainlink": {
      "name": "Chainlink",
      "symbol": "LINK",
      "is_real_ai": false,
      "ai_type": "other",
      "ai_summary": "Decentralized oracle network for smart contracts, not AI infrastructure despite data capabilities.",
      "ai_score": 15,
      "company": "Chainlink Labs",
      "price_usd": 9.68,
      "mcap_m": 7032.0,
      "change_24h": -0.66,
      "change_7d": -9.62,
      "volume_m": 241.3,
      "verified": false,
      "updated_at": "2025-01-07T00:00:00Z"
    },
    "staked-tao-root": {
      "name": "Staked TAO (Root)",
      "symbol": "SN0",
      "is_real_ai": true,
      "ai_type": "compute",
      "ai_summary": "Liquid staking derivative for Bittensor TAO, enabling participation in decentralized AI network.",
      "ai_score": 75,
      "company": null,
      "price_usd": 269.08,
      "mcap_m": 1626.0,
      "change_24h": -2.19,
      "change_7d": -17.8,
      "volume_m": 26.4,
      "verified": false,
      "updated_at": "2025-01-07T00:00:00Z"
    },
    "kite-2": {
      "name": "Kite",
      "symbol": "KITE",
      "is_real_ai": false,
      "ai_type": "other",
      "ai_summary": "Insufficient information to verify real AI infrastructure; appears to be speculative token.",
      "ai_score": 10,
      "company": null,
      "price_usd": 0.212771,
      "mcap_m": 483.9,
      "change_24h": -0.84,
      "change_7d": 16.74,
      "volume_m": 36.3,
      "verified": false,
      "updated_at": "2025-01-07T00:00:00Z"
    },
    "unibase": {
      "name": "Unibase",
      "symbol": "UB",
      "is_real_ai": false,
      "ai_type": "other",
      "ai_summary": "No verifiable AI infrastructure development; likely generic crypto project.",
      "ai_score": 5,
      "company": null,
      "price_usd": 0.156867,
      "mcap_m": 391.0,
      "change_24h": -9.37,
      "change_7d": 17.12,
      "volume_m": 24.2,
      "verified": false,
      "updated_at": "2025-01-07T00:00:00Z"
    },
    "pieverse": {
      "name": "Pieverse",
      "symbol": "PIEVERSE",
      "is_real_ai": false,
      "ai_type": "other",
      "ai_summary": "Appears to be metaverse/gaming project without substantive AI infrastructure.",
      "ai_score": 8,
      "company": null,
      "price_usd": 0.918809,
      "mcap_m": 247.5,
      "change_24h": 2.7,
      "change_7d": 14.95,
      "volume_m": 8.5,
      "verified": false,
      "updated_at": "2025-01-07T00:00:00Z"
    },
    "theta-token": {
      "name": "Theta Network",
      "symbol": "THETA",
      "is_real_ai": false,
      "ai_type": "other",
      "ai_summary": "Decentralized video streaming network, not AI infrastructure despite edge computing.",
      "ai_score": 12,
      "company": "Theta Labs",
      "price_usd": 0.196362,
      "mcap_m": 196.5,
      "change_24h": -4.68,
      "change_7d": -16.42,
      "volume_m": 6.5,
      "verified": false,
      "updated_at": "2025-01-07T00:00:00Z"
    },
    "story-2": {
      "name": "Story",
      "symbol": "IP",
      "is_real_ai": false,
      "ai_type": "other",
      "ai_summary": "IP protocol for programmable intellectual property, not AI infrastructure.",
      "ai_score": 20,
      "company": "Story Protocol",
      "price_usd": 0.49252,
      "mcap_m": 174.2,
      "change_24h": -1.37,
      "change_7d": -15.68,
      "volume_m": 24.6,
      "verified": false,
      "updated_at": "2025-01-07T00:00:00Z"
    }
  }
}